LICENSE.txt
README.md
setup.py
yy_vtm/__init__.py
yy_vtm/maker.py
yy_vtm.egg-info/PKG-INFO
yy_vtm.egg-info/SOURCES.txt
yy_vtm.egg-info/dependency_links.txt
yy_vtm.egg-info/entry_points.txt
yy_vtm.egg-info/requires.txt
yy_vtm.egg-info/top_level.txt