Metadata-Version: 2.1
Name: yy-vtm
Version: 0.3
Summary: Make video thumbnail
Home-page: https://github.com/youyinnn/yy_vtm
Author: Jun
Author-email: youyinnn@gmail.com
License: MIT
Keywords: video,thumbnail,maker
Classifier: Development Status :: 3 - Alpha
Classifier: Intended Audience :: Developers
Classifier: Topic :: Software Development :: Build Tools
Classifier: License :: OSI Approved :: MIT License
Classifier: Programming Language :: Python :: 3
Classifier: Programming Language :: Python :: 3.4
Classifier: Programming Language :: Python :: 3.5
Classifier: Programming Language :: Python :: 3.6
License-File: LICENSE.txt
